demo.py
teamB_package-0.0.1.dist-info/LICENSE.txt
teamB_package-0.0.1.dist-info/METADATA
teamB_package-0.0.1.dist-info/WHEEL
teamB_package-0.0.1.dist-info/top_level.txt
teamB_package-0.0.1.dist-info/RECORD
