Metadata-Version: 2.1
Name: teamB-package
Version: 0.0.1
Summary: Say hello!
Home-page: UNKNOWN
License: UNKNOWN
Platform: UNKNOWN
License-File: LICENSE.txt
